{
  "dense_units1": 2,
  "dropout1": 0.3,
  "activation1": "relu",
  "dense_units2": 4,
  "dropout2": 0,
  "activation2": "relu",
  "dense_units3": 2,
  "dropout3": 0,
  "activation3": "relu",
  "dense_units4": 4,
  "dropout4": 0,
  "activation4": "relu",
  "loss": "mse",
  "epochs": 50,
  "batch_size": 128,
  "learning_rate": 0.005,
  "CD3_loss": 1,
  "CD19_loss": 1,
  "CD45RA_loss": 1,
  "CD4_loss": 1,
  "CD8a_loss": 1,
  "CD14_loss": 1,
  "CD45RO_loss": 1,
  "CD279_PD_1_loss": 1,
  "IgG1_loss": 1,
  "IgG2a_loss": 1,
  "IgG2b_loss": 1,
  "CD127_loss": 1,
  "CD197_CR7_loss": 1,
  "HLA_DR_loss": 1
}
